tests/__init__.py
tests/test_pyspark.py
tests/test_sample.py
unittest_pyspark/__init__.py
unittest_pyspark/pyspark.py
unittest_pyspark/unittest.py
unittest_pyspark-0.0.5.dist-info/LICENSE
unittest_pyspark-0.0.5.dist-info/METADATA
unittest_pyspark-0.0.5.dist-info/WHEEL
unittest_pyspark-0.0.5.dist-info/top_level.txt
unittest_pyspark-0.0.5.dist-info/RECORD
