Metadata-Version: 2.1
Name: unittest-pyspark
Version: 0.0.5
Summary: Extension to unittest for pySpark
Home-page: https://github.com/ivangeorgiev/unittest-pyspark
Author: Ivan Georgiev
Author-email: ivan.georgiev@gmail.com
License: UNKNOWN
Platform: UNKNOWN
Classifier: Programming Language :: Python :: 3
Classifier: License :: OSI Approved :: GNU General Public License (GPL)
Classifier: Operating System :: OS Independent
Requires-Python: >=3.6
